[
  {"name": "Godrick the Grafted", "region": "Stormveil Castle", "type": "Shardbearer", "damage": "Physical/Fire", "Remembrance": true},
  {"name": "Rennala, Queen of the Full Moon", "region": "Raya Lucaria Academy", "type": "Shardbearer", "damage": "Magic", "Remembrance": true},
  {"name": "Starscourge Radahn", "region": "Caelid", "type": "Shardbearer", "damage": "Gravity", "Remembrance": true},
  {"name": "Morgott, the Omen King", "region": "Leyndell, Royal Capital", "type": "Shardbearer", "damage": "Physical/Death", "Remembrance": true},
  {"name": "Malenia, Blade of Miquella", "region": "Miquella's Haligtree", "type": "Shardbearer", "damage": "Scarlet Rot", "Remembrance": true},
  {"name": "Mohg, Lord of Blood", "region": "Mohgwyn Palace", "type": "Shardbearer", "damage": "Blood", "Remembrance": true},
  {"name": "Rykard, Lord of Blasphemy", "region": "Volcano Manor", "type": "Shardbearer", "damage": "Fire", "Remembrance": true},
  {"name": "Godfrey, First Elden Lord", "region": "Leyndell, Royal Capital", "type": "Shardbearer", "damage": "Physical/Holy", "Remembrance": true},
  {"name": "Radagon of the Golden Order", "region": "Leyndell, Royal Capital", "type": "Shardbearer", "damage": "Physical/Holy", "Remembrance": true},
  {"name": "Elden Beast", "region": "Leyndell, Royal Capital", "type": "Final Boss", "damage": "Holy", "Remembrance": false},
  {"name": "Margit, the Fell Omen", "region": "Stormveil Castle", "type": "Legend", "damage": "Physical/Lightning", "Remembrance": false},
  {"name": "Grafted Scion", "region": "Chapel of Anticipation", "type": "Legend", "damage": "Physical", "Remembrance": false},
  {"name": "Flying Dragon Agheel", "region": "Limgrave", "type": "Dragon", "damage": "Fire", "Remembrance": false},
  {"name": "Tree Sentinel", "region": "Limgrave", "type": "Field Boss", "damage": "Physical/Holy", "Remembrance": false},
  {"name": "Bloodhound Knight Darriwil", "region": "Limgrave", "type": "Evergaol", "damage": "Bleed", "Remembrance": false},
  {"name": "Crucible Knight", "region": "Stormhill", "type": "Field Boss", "damage": "Physical/Holy", "Remembrance": false},
  {"name": "Demi-Human Chief", "region": "Limgrave", "type": "Field Boss", "damage": "Physical", "Remembrance": false},
  {"name": "Erdtree Burial Watchdog", "region": "Limgrave", "type": "Field Boss", "damage": "Physical/Fire", "Remembrance": false},
  {"name": "Guardian Golem", "region": "Limgrave", "type": "Field Boss", "damage": "Physical", "Remembrance": false},
  {"name": "Mad Pumpkin Head", "region": "Limgrave", "type": "Field Boss", "damage": "Physical", "Remembrance": false},
  {"name": "Patches", "region": "Limgrave", "type": "Field Boss", "damage": "Physical", "Remembrance": false},
  {"name": "Bell Bearing Hunter", "region": "Limgrave", "type": "Field Boss", "damage": "Physical", "Remembrance": false},
  {"name": "Black Knife Assassin", "region": "Limgrave", "type": "Field Boss", "damage": "Physical/Poison", "Remembrance": false},
  {"name": "Leonine Misbegotten", "region": "Weeping Peninsula", "type": "Field Boss", "damage": "Physical", "Remembrance": false},
  {"name": "Miranda Blossom", "region": "Weeping Peninsula", "type": "Field Boss", "damage": "Poison", "Remembrance": false},
  {"name": "Runebear", "region": "Weeping Peninsula", "type": "Field Boss", "damage": "Physical", "Remembrance": false},
  {"name": "Scaly Misbegotten", "region": "Weeping Peninsula", "type": "Field Boss", "damage": "Physical", "Remembrance": false},
  {"name": "Stonedigger Troll", "region": "Weeping Peninsula", "type": "Field Boss", "damage": "Physical", "Remembrance": false},
  {"name": "Adan, Thief of Fire", "region": "Liurnia of the Lakes", "type": "Field Boss", "damage": "Fire", "Remembrance": false},
  {"name": "Alecto, Black Knife Ringleader", "region": "Liurnia of the Lakes", "type": "Field Boss", "damage": "Physical/Poison", "Remembrance": false},
  {"name": "Bell Bearing Hunter", "region": "Liurnia of the Lakes", "type": "Field Boss", "damage": "Physical", "Remembrance": false},
  {"name": "Black Knife Assassin", "region": "Liurnia of the Lakes", "type": "Field Boss", "damage": "Physical/Poison", "Remembrance": false},
  {"name": "Bloodhound Knight", "region": "Liurnia of the Lakes", "type": "Field Boss", "damage": "Physical", "Remembrance": false},
  {"name": "Bols, Carian Knight", "region": "Liurnia of the Lakes", "type": "Field Boss", "damage": "Physical", "Remembrance": false},
  {"name": "Cemetery Shade", "region": "Liurnia of the Lakes", "type": "Field Boss", "damage": "Physical/Death", "Remembrance": false},
  {"name": "Cleanrot Knight", "region": "Liurnia of the Lakes", "type": "Field Boss", "damage": "Physical/Poison", "Remembrance": false},
  {"name": "Crystalian", "region": "Liurnia of the Lakes", "type": "Field Boss", "damage": "Physical", "Remembrance": false},
  {"name": "Death Rite Bird", "region": "Liurnia of the Lakes", "type": "Field Boss", "damage": "Physical/Death", "Remembrance": false},
  {"name": "Deathbird", "region": "Limgrave, Liurnia of the Lakes", "type": "Field Boss", "damage": "Physical/Death", "Remembrance": false},
  {"name": "Erdtree Avatar", "region": "Liurnia of the Lakes", "type": "Field Boss", "damage": "Physical/Holy", "Remembrance": false},
  {"name": "Erdtree Burial Watchdog", "region": "Liurnia of the Lakes", "type": "Field Boss", "damage": "Physical/Fire", "Remembrance": false},
  {"name": "Glintstone Dragon Adula", "region": "Liurnia of the Lakes", "type": "Dragon", "damage": "Magic/Physical", "Remembrance": false},
  {"name": "Glintstone Dragon Smarag", "region": "Liurnia of the Lakes", "type": "Dragon", "damage": "Magic/Physical", "Remembrance": false},
  {"name": "Magma Wyrm Makar", "region": "Liurnia of the Lakes", "type": "Field Boss", "damage": "Fire/Physical", "Remembrance": false},
  {"name": "Omenkiller", "region": "Liurnia of the Lakes", "type": "Field Boss", "damage": "Physical", "Remembrance": false},
  {"name": "Onyx Lord", "region": "Liurnia of the Lakes", "type": "Field Boss", "damage": "Magic/Physical", "Remembrance": false},
  {"name": "Royal Knight Loretta", "region": "Liurnia of the Lakes", "type": "Field Boss", "damage": "Magic/Physical", "Remembrance": false},
  {"name": "Royal Revenant", "region": "Liurnia of the Lakes", "type": "Field Boss", "damage": "Physical/Poison", "Remembrance": false},
  {"name": "Soldier Of Godrick", "region": "Limgrave", "type": "Tutorial Boss", "damage": "Physical", "Remembrance": false}
]
